COPYING
MANIFEST.in
README.rst
bootstrap.py
buildout.cfg
setup.py
docs/conf.py
docs/index.rst
xbob/__init__.py
xbob.db.nist_sre12.egg-info/PKG-INFO
xbob.db.nist_sre12.egg-info/SOURCES.txt
xbob.db.nist_sre12.egg-info/dependency_links.txt
xbob.db.nist_sre12.egg-info/entry_points.txt
xbob.db.nist_sre12.egg-info/namespace_packages.txt
xbob.db.nist_sre12.egg-info/not-zip-safe
xbob.db.nist_sre12.egg-info/requires.txt
xbob.db.nist_sre12.egg-info/top_level.txt
xbob/db/__init__.py
xbob/db/nist_sre12/__init__.py
xbob/db/nist_sre12/create.py
xbob/db/nist_sre12/db.sql3
xbob/db/nist_sre12/driver.py
xbob/db/nist_sre12/models.py
xbob/db/nist_sre12/query.py
xbob/db/nist_sre12/test.py
xbob/db/nist_sre12/noise_description/NoisySetDescription.lst
xbob/db/nist_sre12/prism/LOGS
xbob/db/nist_sre12/prism/all_files.lst
xbob/db/nist_sre12/prism/protocols/female/dev/for_models.lst
xbob/db/nist_sre12/prism/protocols/female/dev/for_probes.lst
xbob/db/nist_sre12/prism/protocols/female/dev/for_tnorm.lst
xbob/db/nist_sre12/prism/protocols/female/dev/for_znorm.lst
xbob/db/nist_sre12/prism/protocols/female/eval/for_models.lst
xbob/db/nist_sre12/prism/protocols/female/eval/for_probes.lst
xbob/db/nist_sre12/prism/protocols/female/eval/for_tnorm.lst
xbob/db/nist_sre12/prism/protocols/female/eval/for_znorm.lst
xbob/db/nist_sre12/prism/protocols/female/norm/train_optional_world_1.lst
xbob/db/nist_sre12/prism/protocols/female/norm/train_optional_world_1.lst.GD
xbob/db/nist_sre12/prism/protocols/female/norm/train_optional_world_2.lst
xbob/db/nist_sre12/prism/protocols/female/norm/train_optional_world_2.lst.GD
xbob/db/nist_sre12/prism/protocols/female/norm/train_world.lst
xbob/db/nist_sre12/prism/protocols/female/norm/train_world.lst.GD
xbob/db/nist_sre12/prism/protocols/male/dev/for_models.lst
xbob/db/nist_sre12/prism/protocols/male/dev/for_probes.lst
xbob/db/nist_sre12/prism/protocols/male/dev/for_tnorm.lst
xbob/db/nist_sre12/prism/protocols/male/dev/for_znorm.lst
xbob/db/nist_sre12/prism/protocols/male/eval/for_models.lst
xbob/db/nist_sre12/prism/protocols/male/eval/for_probes.lst
xbob/db/nist_sre12/prism/protocols/male/eval/for_tnorm.lst
xbob/db/nist_sre12/prism/protocols/male/eval/for_znorm.lst
xbob/db/nist_sre12/prism/protocols/male/norm/train_optional_world_1.lst
xbob/db/nist_sre12/prism/protocols/male/norm/train_optional_world_1.lst.GD
