Metadata-Version: 1.1
Name: xbob.db.nist-sre12
Version: 1.2.0
Summary: Speaker verification protocol on the NIST SRE 2012
Home-page: https://pypi.python.org/pypi/xbob.db.nist_sre12/
Author: Elie Khoury
Author-email: Elie.Khoury@idiap.ch
License: GPLv3
Keywords: Spear,Speaker Recognition,Speaker verification,Gaussian Mixture Model,ISV,UBM-GMM,I-Vector,Audio processing,NIST SRE 2012,Database
Platform: UNKNOWN
Classifier: Development Status :: 4 - Beta
Classifier: Environment :: Console
Classifier: Intended Audience :: Developers
Classifier: Intended Audience :: Education
Classifier: Intended Audience :: Science/Research
Classifier: License :: OSI Approved :: GNU General Public License v3 (GPLv3)
Classifier: Natural Language :: English
Classifier: Programming Language :: Python
Classifier: Programming Language :: Python :: 3
Classifier: Topic :: Scientific/Engineering :: Artificial Intelligence
Classifier: Topic :: Database :: Front-Ends
